PhantomDecoders.py
phantomdecoders-1.6.7.dist-info/LICENSE
phantomdecoders-1.6.7.dist-info/METADATA
phantomdecoders-1.6.7.dist-info/WHEEL
phantomdecoders-1.6.7.dist-info/RECORD
